{
    "help.title": "Livre d'aide",
    "help.arguments": "[Facultatif] | <Obligatoire>",
    "help.command-embed.title": "Aide sur la commande `{name}`.",
    "help.command-embed.info": "Informations",
    "help.command-embed.category": "Catégorie : `{category_emoji}{category_name}`\n",
    "help.command-embed.aliases": "Alias : {alias}\n",
    "help.command-embed.disable_command": "Puis-je l'éteindre ? **{value}**\n",
    "help.command-embed.connection_disabled.0": "Non",
    "help.command-embed.connection_disabled.1": "Ouais",
    "help.command-embed.using_command": "Utilisation : `{using}`\n",
    "help.command-embed.example": "Example №{number}",
    "help.command-notfound.title": "Commande non trouvée",
    "help.command-notfound.description": "Lors de la recherche d'une commande, nous ne l'avons pas trouvée, regardez-la à nouveau dans la liste générale des commandes",
    "help.command-invalid.title": "La commande n'est pas valide",
    "help.command-invalid.description": "Il est fort probable que vous ayez mal saisi le nom de l'équipe, il contient peut-être des caractères étranges."
}